odoo/addons/contract_variable_qty_timesheet/README.rst
odoo/addons/contract_variable_qty_timesheet/__init__.py
odoo/addons/contract_variable_qty_timesheet/__manifest__.py
odoo/addons/contract_variable_qty_timesheet/data/contract_line_qty_formula_data.xml
odoo/addons/contract_variable_qty_timesheet/i18n/contract_variable_qty_timesheet.pot
odoo/addons/contract_variable_qty_timesheet/i18n/de.po
odoo/addons/contract_variable_qty_timesheet/i18n/es.po
odoo/addons/contract_variable_qty_timesheet/i18n/fr.po
odoo/addons/contract_variable_qty_timesheet/i18n/it.po
odoo/addons/contract_variable_qty_timesheet/i18n/pt.po
odoo/addons/contract_variable_qty_timesheet/i18n/pt_BR.po
odoo/addons/contract_variable_qty_timesheet/i18n/zh.po
odoo/addons/contract_variable_qty_timesheet/readme/CONTRIBUTORS.rst
odoo/addons/contract_variable_qty_timesheet/readme/DESCRIPTION.rst
odoo/addons/contract_variable_qty_timesheet/readme/USAGE.rst
odoo/addons/contract_variable_qty_timesheet/static/description/icon.png
odoo/addons/contract_variable_qty_timesheet/static/description/index.html
odoo/addons/contract_variable_qty_timesheet/tests/__init__.py
odoo/addons/contract_variable_qty_timesheet/tests/test_contract_variable_qty_timesheet.py
odoo12_addon_contract_variable_qty_timesheet-12.0.1.0.1.dist-info/METADATA
odoo12_addon_contract_variable_qty_timesheet-12.0.1.0.1.dist-info/WHEEL
odoo12_addon_contract_variable_qty_timesheet-12.0.1.0.1.dist-info/top_level.txt
odoo12_addon_contract_variable_qty_timesheet-12.0.1.0.1.dist-info/RECORD
